sun/__init__.py
sun/__metadata__.py
sun/about.py
sun/autostart.py
sun/configs.py
sun/daemon.py
sun/sys_info.py
sun/utils.py
sun/cli/__init__.py
sun/cli/tool.py
sun/tray_app/__init__.py
sun/tray_app/tray_icon.py
sun-2.0.3.dist-info/entry_points.txt
sun-2.0.3.dist-info/licenses/LICENSE.txt
sun-2.0.3.dist-info/WHEEL
sun-2.0.3.dist-info/METADATA
sun-2.0.3.dist-info/RECORD
